{"_cached_at":1778516820432,"v":{"_source":"api.github.com","_fetched_at":"2026-05-11T16:27:00.432Z","repo_archived":false,"owner_type":"User","last_commit_iso":"2026-05-11T05:25:21.000Z","days_since_last_commit":0,"default_branch":"main","default_branch_last_ci_status":"QUEUED","default_branch_last_ci_run_at":"2026-05-11T05:25:25Z","last_release_iso":"2026-05-09T13:09:08Z","releases_total":41,"open_issues":261,"closed_issues":72,"open_prs":50,"closed_prs":1083,"merged_prs_12mo":333,"issues_closed_12mo":null,"issues_opened_12mo":null,"oldest_open_issue_age_days":2528,"committers_12mo":11,"commits_12mo":26,"commits_12mo_truncated":false,"top_committer_commit_share_12mo":0.46153846153846156,"top3_committer_commit_share_12mo":0.6923076923076923,"has_discussions_enabled":true}}