{"_cached_at":1778531911591,"v":{"_source":"api.github.com","_fetched_at":"2026-05-11T20:38:31.591Z","repo_archived":false,"owner_type":"Organization","last_commit_iso":"2026-04-29T08:32:31.000Z","days_since_last_commit":12,"default_branch":"main","default_branch_last_ci_status":"SUCCESS","default_branch_last_ci_run_at":"2026-05-04T22:57:52Z","last_release_iso":null,"releases_total":0,"open_issues":3,"closed_issues":89,"open_prs":3,"closed_prs":331,"merged_prs_12mo":31,"issues_closed_12mo":null,"issues_opened_12mo":null,"oldest_open_issue_age_days":733,"committers_12mo":6,"commits_12mo":43,"commits_12mo_truncated":false,"top_committer_commit_share_12mo":0.5581395348837209,"top2_committer_commit_share_12mo":0.8372093023255814,"top3_committer_commit_share_12mo":0.9302325581395349,"top_committers_12mo":[{"login":"login:sassbot","commits":24,"share":0.5581395348837209},{"login":"login:nex3","commits":12,"share":0.27906976744186046},{"login":"login:ntkme","commits":4,"share":0.09302325581395349},{"login":"login:Goodwine","commits":1,"share":0.023255813953488372},{"login":"login:Trott","commits":1,"share":0.023255813953488372}],"has_discussions_enabled":false}}