{"_cached_at":1778522986729,"v":{"_source":"api.github.com","_fetched_at":"2026-05-11T18:09:46.729Z","repo_archived":false,"owner_type":"Organization","last_commit_iso":"2026-05-11T16:31:05.000Z","days_since_last_commit":0,"default_branch":"main","default_branch_last_ci_status":"NEUTRAL","default_branch_last_ci_run_at":"2026-05-11T17:14:25Z","last_release_iso":"2026-04-15T11:44:13Z","releases_total":451,"open_issues":104,"closed_issues":10079,"open_prs":94,"closed_prs":8438,"merged_prs_12mo":802,"issues_closed_12mo":null,"issues_opened_12mo":null,"oldest_open_issue_age_days":4302,"committers_12mo":47,"commits_12mo":689,"commits_12mo_truncated":false,"top_committer_commit_share_12mo":0.5007256894049347,"top3_committer_commit_share_12mo":0.8127721335268505,"has_discussions_enabled":true}}