{"_cached_at":1778519511219,"v":{"versionKey":{"system":"NPM","name":"formidable","version":"3.5.4"},"publishedAt":"2025-04-23T01:58:45Z","isDefault":true,"isDeprecated":false,"deprecatedReason":"","licenses":["MIT"],"advisoryKeys":[],"links":[{"label":"HOMEPAGE","url":"https://github.com/node-formidable/formidable"},{"label":"ORIGIN","url":"https://registry.npmjs.org/formidable/3.5.4"},{"label":"SOURCE_REPO","url":"node-formidable/formidable"}],"slsaProvenances":[],"attestations":[],"registries":["https://registry.npmjs.org/"],"relatedProjects":[]}}