{"_cached_at":1778516783761,"v":{"versionKey":{"system":"NPM","name":"@gerrit0/mini-shiki","version":"3.23.0"},"publishedAt":"2026-02-26T00:16:50Z","isDefault":true,"isDeprecated":false,"deprecatedReason":"","licenses":["MIT"],"advisoryKeys":[],"links":[{"label":"HOMEPAGE","url":"https://github.com/Gerrit0/mini-shiki#readme"},{"label":"ISSUE_TRACKER","url":"https://github.com/Gerrit0/mini-shiki/issues"},{"label":"ATTESTATION","url":"https://registry.npmjs.org/-/npm/v1/attestations/@gerrit0%2fmini-shiki@3.23.0"},{"label":"ORIGIN","url":"https://registry.npmjs.org/@gerrit0%2Fmini-shiki/3.23.0"},{"label":"SOURCE_REPO","url":"git+https://github.com/Gerrit0/mini-shiki.git"}],"slsaProvenances":[{"sourceRepository":"https://github.com/Gerrit0/mini-shiki","commit":"c86246b920421745f76c9d729ab5c27557828aa5","url":"https://registry.npmjs.org/-/npm/v1/attestations/@gerrit0%2fmini-shiki@3.23.0","verified":true}],"attestations":[{"type":"https://slsa.dev/provenance/v1","url":"https://registry.npmjs.org/-/npm/v1/attestations/@gerrit0%2fmini-shiki@3.23.0","verified":true,"sourceRepository":"https://github.com/Gerrit0/mini-shiki","commit":"c86246b920421745f76c9d729ab5c27557828aa5"}],"registries":["https://registry.npmjs.org/"],"relatedProjects":[{"projectKey":{"id":"github.com/gerrit0/mini-shiki"},"relationProvenance":"UNVERIFIED_METADATA","relationType":"ISSUE_TRACKER"},{"projectKey":{"id":"github.com/gerrit0/mini-shiki"},"relationProvenance":"UNVERIFIED_METADATA","relationType":"SOURCE_REPO"},{"projectKey":{"id":"github.com/gerrit0/mini-shiki"},"relationProvenance":"SLSA_ATTESTATION","relationType":"SOURCE_REPO"}]}}