{"_cached_at":1778520662779,"v":{"versionKey":{"system":"NPM","name":"node-releases","version":"2.0.36"},"publishedAt":"2026-03-04T03:59:16Z","isDefault":false,"isDeprecated":false,"deprecatedReason":"","licenses":["MIT"],"advisoryKeys":[],"links":[{"label":"HOMEPAGE","url":"https://github.com/chicoxyzzy/node-releases#readme"},{"label":"ISSUE_TRACKER","url":"https://github.com/chicoxyzzy/node-releases/issues"},{"label":"ORIGIN","url":"https://registry.npmjs.org/node-releases/2.0.36"},{"label":"SOURCE_REPO","url":"git+https://github.com/chicoxyzzy/node-releases.git"}],"slsaProvenances":[],"attestations":[],"registries":["https://registry.npmjs.org/"],"relatedProjects":[{"projectKey":{"id":"github.com/chicoxyzzy/node-releases"},"relationProvenance":"UNVERIFIED_METADATA","relationType":"ISSUE_TRACKER"},{"projectKey":{"id":"github.com/chicoxyzzy/node-releases"},"relationProvenance":"UNVERIFIED_METADATA","relationType":"SOURCE_REPO"}]}}