{"_cached_at":1778518498046,"v":{"versionKey":{"system":"NPM","name":"@types/hoist-non-react-statics","version":"3.3.7"},"publishedAt":"2025-07-21T13:15:01Z","isDefault":true,"isDeprecated":false,"deprecatedReason":"","licenses":["MIT"],"advisoryKeys":[],"links":[{"label":"HOMEPAGE","url":"https://github.com/DefinitelyTyped/DefinitelyTyped/tree/master/types/hoist-non-react-statics"},{"label":"ORIGIN","url":"https://registry.npmjs.org/@types%2Fhoist-non-react-statics/3.3.7"},{"label":"SOURCE_REPO","url":"https://github.com/DefinitelyTyped/DefinitelyTyped.git"}],"slsaProvenances":[],"attestations":[],"registries":["https://registry.npmjs.org/"],"relatedProjects":[{"projectKey":{"id":"github.com/definitelytyped/definitelytyped"},"relationProvenance":"UNVERIFIED_METADATA","relationType":"SOURCE_REPO"}]}}