{"_cached_at":1778520443395,"v":{"versionKey":{"system":"NPM","name":"listr2","version":"9.0.5"},"publishedAt":"2025-10-20T13:52:02Z","isDefault":false,"isDeprecated":false,"deprecatedReason":"","licenses":["MIT"],"advisoryKeys":[],"links":[{"label":"HOMEPAGE","url":"https://github.com/listr2/listr2#readme"},{"label":"ISSUE_TRACKER","url":"https://github.com/listr2/listr2/issues"},{"label":"ORIGIN","url":"https://registry.npmjs.org/listr2/9.0.5"},{"label":"SOURCE_REPO","url":"git+https://github.com/listr2/listr2.git"}],"slsaProvenances":[],"attestations":[],"registries":["https://registry.npmjs.org/"],"relatedProjects":[{"projectKey":{"id":"github.com/listr2/listr2"},"relationProvenance":"UNVERIFIED_METADATA","relationType":"ISSUE_TRACKER"},{"projectKey":{"id":"github.com/listr2/listr2"},"relationProvenance":"UNVERIFIED_METADATA","relationType":"SOURCE_REPO"}]}}