{"_cached_at":1778521079677,"v":{"versionKey":{"system":"NPM","name":"rehackt","version":"0.1.0"},"publishedAt":"2024-04-23T08:55:04Z","isDefault":true,"isDeprecated":false,"deprecatedReason":"","licenses":["MIT"],"advisoryKeys":[],"links":[{"label":"HOMEPAGE","url":"https://github.com/phryneas/rehackt"},{"label":"ISSUE_TRACKER","url":"https://github.com/phryneas/rehackt/issues"},{"label":"ATTESTATION","url":"https://registry.npmjs.org/-/npm/v1/attestations/rehackt@0.1.0"},{"label":"ORIGIN","url":"https://registry.npmjs.org/rehackt/0.1.0"},{"label":"SOURCE_REPO","url":"git+https://github.com/phryneas/rehackt.git"}],"slsaProvenances":[{"sourceRepository":"https://github.com/phryneas/rehackt","commit":"1150f7e2b8dae52ba5231bde1a42595839dd9603","url":"https://registry.npmjs.org/-/npm/v1/attestations/rehackt@0.1.0","verified":true}],"attestations":[{"type":"https://slsa.dev/provenance/v1","url":"https://registry.npmjs.org/-/npm/v1/attestations/rehackt@0.1.0","verified":true,"sourceRepository":"https://github.com/phryneas/rehackt","commit":"1150f7e2b8dae52ba5231bde1a42595839dd9603"}],"registries":["https://registry.npmjs.org/"],"relatedProjects":[{"projectKey":{"id":"github.com/phryneas/rehackt"},"relationProvenance":"UNVERIFIED_METADATA","relationType":"ISSUE_TRACKER"},{"projectKey":{"id":"github.com/phryneas/rehackt"},"relationProvenance":"UNVERIFIED_METADATA","relationType":"SOURCE_REPO"},{"projectKey":{"id":"github.com/phryneas/rehackt"},"relationProvenance":"SLSA_ATTESTATION","relationType":"SOURCE_REPO"}]}}