{"_cached_at":1778517176292,"v":{"versionKey":{"system":"NPM","name":"@jsonjoy.com/fs-core","version":"4.57.1"},"publishedAt":"2026-03-21T17:20:13Z","isDefault":false,"isDeprecated":false,"deprecatedReason":"","licenses":["Apache-2.0"],"advisoryKeys":[],"links":[{"label":"HOMEPAGE","url":"https://github.com/streamich/memfs/tree/master/packages/fs-core"},{"label":"ISSUE_TRACKER","url":"https://github.com/streamich/memfs/issues"},{"label":"ATTESTATION","url":"https://registry.npmjs.org/-/npm/v1/attestations/@jsonjoy.com%2ffs-core@4.57.1"},{"label":"ORIGIN","url":"https://registry.npmjs.org/@jsonjoy.com%2Ffs-core/4.57.1"},{"label":"SOURCE_REPO","url":"git+https://github.com/streamich/memfs.git"}],"slsaProvenances":[{"sourceRepository":"https://github.com/streamich/memfs","commit":"e712f63a3539ae96d1de013feef14e0cf15d1a2c","url":"https://registry.npmjs.org/-/npm/v1/attestations/@jsonjoy.com%2ffs-core@4.57.1","verified":true}],"attestations":[{"type":"https://slsa.dev/provenance/v1","url":"https://registry.npmjs.org/-/npm/v1/attestations/@jsonjoy.com%2ffs-core@4.57.1","verified":true,"sourceRepository":"https://github.com/streamich/memfs","commit":"e712f63a3539ae96d1de013feef14e0cf15d1a2c"}],"registries":["https://registry.npmjs.org/"],"relatedProjects":[{"projectKey":{"id":"github.com/streamich/memfs"},"relationProvenance":"UNVERIFIED_METADATA","relationType":"ISSUE_TRACKER"},{"projectKey":{"id":"github.com/streamich/memfs"},"relationProvenance":"UNVERIFIED_METADATA","relationType":"SOURCE_REPO"},{"projectKey":{"id":"github.com/streamich/memfs"},"relationProvenance":"SLSA_ATTESTATION","relationType":"SOURCE_REPO"}]}}