{"_cached_at":1778522966834,"v":{"versionKey":{"system":"NPM","name":"webidl-conversions","version":"7.0.0"},"publishedAt":"2021-09-12T01:03:06Z","isDefault":false,"isDeprecated":false,"deprecatedReason":"","licenses":["BSD-2-Clause"],"advisoryKeys":[],"links":[{"label":"HOMEPAGE","url":"https://github.com/jsdom/webidl-conversions#readme"},{"label":"ISSUE_TRACKER","url":"https://github.com/jsdom/webidl-conversions/issues"},{"label":"ORIGIN","url":"https://registry.npmjs.org/webidl-conversions/7.0.0"},{"label":"SOURCE_REPO","url":"git+https://github.com/jsdom/webidl-conversions.git"}],"slsaProvenances":[],"attestations":[],"registries":["https://registry.npmjs.org/"],"relatedProjects":[{"projectKey":{"id":"github.com/jsdom/webidl-conversions"},"relationProvenance":"UNVERIFIED_METADATA","relationType":"ISSUE_TRACKER"},{"projectKey":{"id":"github.com/jsdom/webidl-conversions"},"relationProvenance":"UNVERIFIED_METADATA","relationType":"SOURCE_REPO"}]}}