{"_cached_at":1778522896341,"v":{"versionKey":{"system":"NPM","name":"unrs-resolver","version":"1.11.1"},"publishedAt":"2025-07-09T14:58:18Z","isDefault":true,"isDeprecated":false,"deprecatedReason":"","licenses":["MIT"],"advisoryKeys":[],"links":[{"label":"HOMEPAGE","url":"https://github.com/unrs/unrs-resolver#readme"},{"label":"ISSUE_TRACKER","url":"https://github.com/unrs/unrs-resolver/issues"},{"label":"ATTESTATION","url":"https://registry.npmjs.org/-/npm/v1/attestations/unrs-resolver@1.11.1"},{"label":"ORIGIN","url":"https://registry.npmjs.org/unrs-resolver/1.11.1"},{"label":"SOURCE_REPO","url":"git+https://github.com/unrs/unrs-resolver.git"}],"slsaProvenances":[{"sourceRepository":"https://github.com/unrs/unrs-resolver","commit":"9480a90b081f2afcaeb6ca0e882d191c138dd7a3","url":"https://registry.npmjs.org/-/npm/v1/attestations/unrs-resolver@1.11.1","verified":true}],"attestations":[{"type":"https://slsa.dev/provenance/v1","url":"https://registry.npmjs.org/-/npm/v1/attestations/unrs-resolver@1.11.1","verified":true,"sourceRepository":"https://github.com/unrs/unrs-resolver","commit":"9480a90b081f2afcaeb6ca0e882d191c138dd7a3"}],"registries":["https://registry.npmjs.org/"],"relatedProjects":[{"projectKey":{"id":"github.com/unrs/unrs-resolver"},"relationProvenance":"UNVERIFIED_METADATA","relationType":"ISSUE_TRACKER"},{"projectKey":{"id":"github.com/unrs/unrs-resolver"},"relationProvenance":"UNVERIFIED_METADATA","relationType":"SOURCE_REPO"},{"projectKey":{"id":"github.com/unrs/unrs-resolver"},"relationProvenance":"SLSA_ATTESTATION","relationType":"SOURCE_REPO"}]}}