{"_cached_at":1778520741061,"v":{"versionKey":{"system":"NPM","name":"p-finally","version":"1.0.0"},"publishedAt":"2016-10-21T06:02:09Z","isDefault":false,"isDeprecated":false,"deprecatedReason":"","licenses":["MIT"],"advisoryKeys":[],"links":[{"label":"HOMEPAGE","url":"https://github.com/sindresorhus/p-finally#readme"},{"label":"ISSUE_TRACKER","url":"https://github.com/sindresorhus/p-finally/issues"},{"label":"ORIGIN","url":"https://registry.npmjs.org/p-finally/1.0.0"},{"label":"SOURCE_REPO","url":"git+https://github.com/sindresorhus/p-finally.git"}],"slsaProvenances":[],"attestations":[],"registries":["https://registry.npmjs.org/"],"relatedProjects":[{"projectKey":{"id":"github.com/sindresorhus/p-finally"},"relationProvenance":"UNVERIFIED_METADATA","relationType":"ISSUE_TRACKER"},{"projectKey":{"id":"github.com/sindresorhus/p-finally"},"relationProvenance":"UNVERIFIED_METADATA","relationType":"SOURCE_REPO"}]}}