{"_cached_at":1778497172510.5896,"v":{"versionKey":{"system":"NPM","name":"memoirist","version":"0.4.0"},"publishedAt":"2025-08-05T17:13:41Z","isDefault":false,"isDeprecated":false,"deprecatedReason":"","licenses":["MIT"],"advisoryKeys":[],"links":[{"label":"HOMEPAGE","url":"https://github.com/SaltyAom/memoirist"},{"label":"ISSUE_TRACKER","url":"https://github.com/SaltyAom/memoirist/issues"},{"label":"ATTESTATION","url":"https://registry.npmjs.org/-/npm/v1/attestations/memoirist@0.4.0"},{"label":"ORIGIN","url":"https://registry.npmjs.org/memoirist/0.4.0"},{"label":"SOURCE_REPO","url":"git+https://github.com/SaltyAom/memoirist.git"}],"slsaProvenances":[{"sourceRepository":"https://github.com/SaltyAom/memoirist","commit":"305173e539b59011f9acdef085f8cff26bf57ab1","url":"https://registry.npmjs.org/-/npm/v1/attestations/memoirist@0.4.0","verified":true}],"attestations":[{"type":"https://slsa.dev/provenance/v1","url":"https://registry.npmjs.org/-/npm/v1/attestations/memoirist@0.4.0","verified":true,"sourceRepository":"https://github.com/SaltyAom/memoirist","commit":"305173e539b59011f9acdef085f8cff26bf57ab1"}],"registries":["https://registry.npmjs.org/"],"relatedProjects":[{"projectKey":{"id":"github.com/saltyaom/memoirist"},"relationProvenance":"UNVERIFIED_METADATA","relationType":"ISSUE_TRACKER"},{"projectKey":{"id":"github.com/saltyaom/memoirist"},"relationProvenance":"UNVERIFIED_METADATA","relationType":"SOURCE_REPO"},{"projectKey":{"id":"github.com/saltyaom/memoirist"},"relationProvenance":"SLSA_ATTESTATION","relationType":"SOURCE_REPO"}]}}