{"_cached_at":1778520967398,"v":{"versionKey":{"system":"NPM","name":"react-animate-height","version":"3.2.3"},"publishedAt":"2023-11-10T09:53:38Z","isDefault":false,"isDeprecated":false,"deprecatedReason":"","licenses":["MIT"],"advisoryKeys":[],"links":[{"label":"HOMEPAGE","url":"https://github.com/Stanko/react-animate-height"},{"label":"ISSUE_TRACKER","url":"https://github.com/Stanko/react-animate-height/issues"},{"label":"ORIGIN","url":"https://registry.npmjs.org/react-animate-height/3.2.3"},{"label":"SOURCE_REPO","url":"git+https://github.com/Stanko/react-animate-height.git"}],"slsaProvenances":[],"attestations":[],"registries":["https://registry.npmjs.org/"],"relatedProjects":[{"projectKey":{"id":"github.com/stanko/react-animate-height"},"relationProvenance":"UNVERIFIED_METADATA","relationType":"ISSUE_TRACKER"},{"projectKey":{"id":"github.com/stanko/react-animate-height"},"relationProvenance":"UNVERIFIED_METADATA","relationType":"SOURCE_REPO"}]}}