{"_cached_at":1778518956508,"v":{"versionKey":{"system":"NPM","name":"content-disposition","version":"0.5.4"},"publishedAt":"2021-12-10T22:55:34Z","isDefault":false,"isDeprecated":false,"deprecatedReason":"","licenses":["MIT"],"advisoryKeys":[],"links":[{"label":"HOMEPAGE","url":"https://github.com/jshttp/content-disposition#readme"},{"label":"ISSUE_TRACKER","url":"https://github.com/jshttp/content-disposition/issues"},{"label":"ORIGIN","url":"https://registry.npmjs.org/content-disposition/0.5.4"},{"label":"SOURCE_REPO","url":"git+https://github.com/jshttp/content-disposition.git"}],"slsaProvenances":[],"attestations":[],"registries":["https://registry.npmjs.org/"],"relatedProjects":[{"projectKey":{"id":"github.com/jshttp/content-disposition"},"relationProvenance":"UNVERIFIED_METADATA","relationType":"ISSUE_TRACKER"},{"projectKey":{"id":"github.com/jshttp/content-disposition"},"relationProvenance":"UNVERIFIED_METADATA","relationType":"SOURCE_REPO"}]}}