{"_cached_at":1778520517346,"v":{"versionKey":{"system":"NPM","name":"markdown-it","version":"14.1.1"},"publishedAt":"2026-02-11T03:49:52Z","isDefault":true,"isDeprecated":false,"deprecatedReason":"","licenses":["MIT"],"advisoryKeys":[],"links":[{"label":"HOMEPAGE","url":"https://github.com/markdown-it/markdown-it#readme"},{"label":"ISSUE_TRACKER","url":"https://github.com/markdown-it/markdown-it/issues"},{"label":"ORIGIN","url":"https://registry.npmjs.org/markdown-it/14.1.1"},{"label":"SOURCE_REPO","url":"git+https://github.com/markdown-it/markdown-it.git"}],"slsaProvenances":[],"attestations":[],"registries":["https://registry.npmjs.org/"],"relatedProjects":[{"projectKey":{"id":"github.com/markdown-it/markdown-it"},"relationProvenance":"UNVERIFIED_METADATA","relationType":"ISSUE_TRACKER"},{"projectKey":{"id":"github.com/markdown-it/markdown-it"},"relationProvenance":"UNVERIFIED_METADATA","relationType":"SOURCE_REPO"}]}}