{"_cached_at":1778518323636,"v":{"_schema":2,"name":"@sindresorhus/is","maintainer_names":["sindresorhus"],"repository_url":"git+https://github.com/sindresorhus/is.git","license":"MIT","deprecated":null,"time":{"created":"2017-09-21T17:54:29.643Z","modified":"2026-05-11T11:22:36.396Z","0.1.0":"2017-09-21T17:54:29.643Z","0.2.0":"2017-09-29T03:22:58.510Z","0.2.1":"2017-10-05T04:21:48.204Z","0.3.0":"2017-10-11T09:51:14.974Z","0.4.0":"2017-10-21T19:28:29.768Z","0.5.0":"2017-11-07T03:23:52.189Z","0.6.0":"2017-11-19T20:18:18.050Z","0.7.0":"2017-12-11T20:40:22.859Z","0.8.0":"2018-04-03T17:10:13.482Z","0.9.0":"2018-05-04T05:31:15.672Z","0.10.0":"2018-07-05T16:33:40.901Z","0.11.0":"2018-07-10T09:56:50.311Z","0.12.0":"2018-09-28T06:36:14.674Z","0.13.0":"2018-11-02T12:10:40.889Z","0.14.0":"2018-12-13T16:00:08.390Z","0.15.0":"2019-02-03T19:55:51.371Z","0.16.0":"2019-05-04T09:15:03.794Z","0.17.0":"2019-05-13T04:08:48.018Z","0.17.1":"2019-05-21T09:49:11.963Z","1.0.0":"2019-06-30T08:25:52.005Z","1.1.0":"2019-10-03T08:02:14.587Z","1.2.0":"2019-10-04T04:40:23.445Z","2.0.0":"2020-01-29T17:47:27.268Z","2.1.0":"2020-02-17T07:23:10.797Z","2.1.1":"2020-04-19T10:21:40.095Z","3.0.0":"2020-06-27T20:55:46.906Z","3.1.0":"2020-07-25T07:15:16.478Z","3.1.1":"2020-08-16T10:31:36.319Z","3.1.2":"2020-08-21T22:25:07.578Z","4.0.0":"2020-10-12T22:09:07.590Z","4.0.1":"2021-04-22T09:01:50.545Z","4.1.0":"2021-09-10T08:32:51.058Z","4.2.0":"2021-09-13T14:28:06.877Z","4.2.1":"2022-01-07T14:48:53.159Z","4.3.0":"2022-01-17T06:08:36.826Z","4.4.0":"2022-01-25T10:30:11.001Z","4.5.0":"2022-02-25T09:16:44.257Z","4.6.0":"2022-02-27T09:06:19.413Z","5.0.0":"2022-06-11T11:20:38.069Z","5.0.1":"2022-06-11T11:28:23.379Z","5.1.0":"2022-06-13T07:09:36.524Z","5.2.0":"2022-06-21T13:27:08.933Z","5.3.0":"2022-07-21T14:31:14.668Z","5.4.0":"2023-05-30T14:18:17.790Z","5.4.1":"2023-06-04T08:04:17.894Z","5.5.0":"2023-07-14T22:34:37.294Z","5.5.1":"2023-07-16T14:48:05.490Z","5.5.2":"2023-07-17T22:47:42.603Z","5.6.0":"2023-07-23T12:44:22.790Z","6.0.0":"2023-08-15T18:52:08.599Z","6.0.1":"2023-10-15T17:06:11.078Z","6.1.0":"2023-10-26T15:03:14.959Z","6.2.0":"2024-02-29T07:31:07.858Z","6.3.0":"2024-04-23T06:01:07.179Z","6.3.1":"2024-05-16T08:15:37.691Z","7.0.0":"2024-07-10T13:43:08.107Z","7.0.1":"2024-09-06T15:55:28.783Z","7.0.2":"2025-06-04T09:58:47.639Z","7.1.0":"2025-09-13T19:21:49.381Z","7.1.1":"2025-10-31T17:26:19.255Z","7.2.0":"2025-12-27T10:44:14.788Z","8.0.0":"2026-04-09T15:11:21.845Z","8.1.0":"2026-05-11T11:22:36.268Z"},"versions_meta":{"0.1.0":{"repository":{"url":"git+https://github.com/sindresorhus/is.git","type":"git"},"license":"MIT","dist":{"integrity":"sha512-lMZXffjDR0kW2SSHJerK+e4r9g0sacKX2zswyDWy6Oi/Ejy8IayLyRyUl3ojPEXoDEwYnhaziRT5m6DkATWLAQ==","shasum":"d0ff822b2b92e6476b7f52ca0f0289992f47061b"}},"0.2.0":{"repository":{"url":"git+https://github.com/sindresorhus/is.git","type":"git"},"license":"MIT","dist":{"integrity":"sha512-3SegjLjiwJUA9kAhfbJmIpE7beMxjdD8gFoiovYYpjsqfvpGPViKwL9haJXG7FmWZxN0xWVd0bDB9quUogQBPQ==","shasum":"c7f5e01c8d3372c682e888f73fd72992514c13c9"}},"0.2.1":{"repository":{"url":"git+https://github.com/sindresorhus/is.git","type":"git"},"license":"MIT","dist":{"integrity":"sha512-uHUsXrbsLFa/qf9JC+961fOyxVLncCrvZ70uI5ZdDVidnkFatnZJoLcyLaAx4A2WrEgRFJckn6yiykZK4RNpdw==","shasum":"537fe5655c9e6b22313776494abc712f0b327e79"}},"0.3.0":{"repository":{"url":"git+https://github.com/sindresorhus/is.git","type":"git"},"license":"MIT","dist":{"integrity":"sha512-oITNea0S2WJA4WCkoiQxjZKPEKkdE/9xYcGxkMu4PqVxaU91541HdudB25Z8im58jJ3z7yOx1WQQG2jWIzZ5xQ==","shasum":"ae248b274cb9eec2d8c7acdf6a70689126ff7237"}},"0.4.0":{"repository":{"url":"git+https://github.com/sindresorhus/is.git","type":"git"},"license":"MIT","dist":{"integrity":"sha512-5WG0MPK5JOCf16GDyP26gmTYI2pMU5eBbiN0bUTb5GzEgBYT7Dj7S7Jjl6dn/pgAXegmACqjD009v5tVFX200g==","shasum":"45bfece11eb55cac415e65b8de352eb75de1b968"}},"0.5.0":{"repository":{"url":"git+https://github.com/sindresorhus/is.git","type":"git"},"license":"MIT","dist":{"integrity":"sha512-6cNJTqnikB7E8BV8kYgoYCAwMBh3QSCUte3fq56ldWASPxrGteIDJR5kJ+BJ+AaTRTzI073VUFMHlWrhACn+Jg==","shasum":"5398b9c4f0963c170d0c8d5873709999f82f508c"}},"0.6.0":{"repository":{"url":"git+https://github.com/sindresorhus/is.git","type":"git"},"license":"MIT","dist":{"integrity":"sha512-KLZFhY/4nJM5wDUSXvPfcwXTlFLkyF3vHQIetYpA19GI1lCpUMp6SuNMVCD4YDEOO/XEqIIwRfPHeoq20kWqNg==","shasum":"383f456b26bc96c7889f0332079f4358b16c58dc"}},"0.7.0":{"repository":{"url":"git+https://github.com/sindresorhus/is.git","type":"git"},"license":"MIT","dist":{"integrity":"sha512-ONhaKPIufzzrlNbqtWFFd+jlnemX6lJAgq9ZeiZtS7I1PIf/la7CW4m83rTXRnVnsMbW2k56pGYu7AUFJD9Pow==","shasum":"9a06f4f137ee84d7df0460c1fdb1135ffa6c50fd"}},"0.8.0":{"repository":{"url":"git+https://github.com/sindresorhus/is.git","type":"git"},"license":"MIT","dist":{"integrity":"sha512-cerdLImrIp8hbt+i2v2rCLCo9fqoRrciP/BzLY3fnmhbwGNDgf7b3Niiqu085+LjPHYxgu0f+3/ciPDPJFgGkA==","shasum":"073aee40b0aab2d4ace33c0a2a2672a37da6fa12"}},"0.9.0":{"repository":{"url":"git+https://github.com/sindresorhus/is.git","type":"git"},"license":"MIT","dist":{"integrity":"sha512-gKDK3XG96qMB3ZEZu9/Qvv6T2x2ZFGn4dcftsItHRF74kA6AqC9DIcOfnzgZSIWsSIHA47soiSNgAEHFxBQ7Fw==","shasum":"1a65a8fab2d4efa5a32a5f5f40cf9b0806aabd69"}},"0.10.0":{"repository":{"url":"git+https://github.com/sindresorhus/is.git","type":"git"},"license":"MIT","dist":{"integrity":"sha512-bmfpY7xAyYhgE531LyMH40uVWgBymnUbL6scPM3pogT/v9CDDnS8N5LRlwLiBGrvjYhBSylIz9P5mIqAMcoKIg==","shasum":"f42dd6a9d12cd79fa6f53b27cf5bea3a30d2cafa"}},"0.11.0":{"repository":{"url":"git+https://github.com/sindresorhus/is.git","type":"git"},"license":"MIT","dist":{"integrity":"sha512-i5Zh5+3QARyXtzq3Bd2Lg3aBRFLcgYbNoap3Hyu1uRN8X+D+0JMqqc4uk4XjhNxfVdCnL8WHUA2wxa33QCC50w==","shasum":"a65970040a5b55c4713452666703b92a6c331fdb"}},"0.12.0":{"repository":{"url":"git+https://github.com/sindresorhus/is.git","type":"git"},"license":"MIT","dist":{"integrity":"sha512-9ve22cGrAKlSRvi8Vb2JIjzcaaQg79531yQHnF+hi/kOpsSj3Om8AyR1wcHrgl0u7U3vYQ7gmF5erZzOp4+51Q==","shasum":"55c37409c809e802efea25911a579731adfc6e07"}},"0.13.0":{"repository":{"url":"git+https://github.com/sindresorhus/is.git","type":"git"},"license":"MIT","dist":{"integrity":"sha512-xTPFzGRnYKVMQlcrVRhO7XIXX5t5hmBC+KpEnlhvjbN1cg5k4qDEVPwzkqhC7jGzmhAY0F9vouWHCt4S/kyeNg==","shasum":"a85d06c13658d0cc9584537df4a99423461f114b"}},"0.14.0":{"repository":{"url":"git+https://github.com/sindresorhus/is.git","type":"git"},"license":"MIT","dist":{"integrity":"sha512-9NET910DNaIPngYnLLPeg+Ogzqsi9uM4mSboU5y6p8S5DzMTVEsJZrawi+BoDNUVBa2DhJqQYUFvMDfgU062LQ==","shasum":"9fb3a3cf3132328151f353de4632e01e52102bea"}},"0.15.0":{"repository":{"url":"git+https://github.com/sindresorhus/is.git","type":"git"},"license":"MIT","dist":{"integrity":"sha512-lu8BpxjAtRCAo5ifytTpCPCj99LF7o/2Myn+NXyNCBqvPYn7Pjd76AMmUB5l7XF1U6t0hcWrlEM5ESufW7wAeA==","shasum":"96915baa05e6a6a1d137badf4984d3fc05820bb6"}},"0.16.0":{"repository":{"url":"git+https://github.com/sindresorhus/is.git","type":"git"},"license":"MIT","dist":{"integrity":"sha512-QjJQRRsPoIBbvI0IFiY1NehCRgyw7BNobGVO9FSuMoX7OocwUMbsjXYFneoYT8XJbiXAEJvPvrj9eEb4ZMa84A==","shasum":"355a7801472ad3810365c1e8aecabcaf45227c54"}},"0.17.0":{"repository":{"url":"git+https://github.com/sindresorhus/is.git","type":"git"},"license":"MIT","dist":{"integrity":"sha512-hGqdhem3E9L+BBPpkRZQ9RtSg+MpbGfoDXNxuPFgJtM7/CiZHU+Jit0DywctJOsWV0jAPp9RpO8QB7GSaVZq8A==","shasum":"37d16c3df3a8b4dcc930210ff68ff3ace35f5ab4"}},"0.17.1":{"repository":{"url":"git+https://github.com/sindresorhus/is.git","type":"git"},"license":"MIT","dist":{"integrity":"sha512-kg/maAZD2Z2AHDFp7cY/ACokjUL0e7MaupTtGXkSW2SV4DJQEHdslFUioP0SMccotjwqTdI0b4XH/qZh6CN+kQ==","shasum":"453b27750f358689c4aa3c9f32d9ace1f0929a79"}},"1.0.0":{"repository":{"url":"git+https://github.com/sindresorhus/is.git","type":"git"},"license":"MIT","dist":{"integrity":"sha512-3rlOB53XCVO7LfjXFx4bCGrZPPjkgYD7pP0E/yo4d57H32aYqD/QNmeXcVnx7CM5SxGScwl2P0b1kCDYZgNWqw==","shasum":"4f475ff3f32b0a309b7faffd33328e93d7953330"}},"1.1.0":{"repository":{"url":"git+https://github.com/sindresorhus/is.git","type":"git"},"license":"MIT","dist":{"integrity":"sha512-6tdrcyVaCv+wo1S2/grH6IBG18ry2lImjU+HUQKAU+GLX3LL959l7OaLUycIPSuQQWTQ9trA0GwrFK7E3PlYeQ==","shasum":"2b4e94c79fa9864d0411a0b9a94e4b8d66b22e28"}},"1.2.0":{"repository":{"url":"git+https://github.com/sindresorhus/is.git","type":"git"},"license":"MIT","dist":{"integrity":"sha512-mwhXGkRV5dlvQc4EgPDxDxO6WuMBVymGFd1CA+2Y+z5dG9MNspoQ+AWjl/Ld1MnpCL8AKbosZlDVohqcIwuWsw==","shasum":"63ce3638cb85231f3704164c90a18ef816da3fb7"}},"2.0.0":{"repository":{"url":"git+https://github.com/sindresorhus/is.git","type":"git"},"license":"MIT","dist":{"integrity":"sha512-bX03FiS5dr3cc01hhymlqDAjO5c5WcRPwY4BrghFFhUWI/3vsVlaq8GiSFsrcA3O07mPedlS6Mnr/whaJ44ubA==","shasum":"1a7d0e05905877a61440d4f15520a5f5b4fedfbf"}},"2.1.0":{"repository":{"url":"git+https://github.com/sindresorhus/is.git","type":"git"},"license":"MIT","dist":{"integrity":"sha512-lXKXfypKo644k4Da4yXkPCrwcvn6SlUW2X2zFbuflKHNjf0w9htru01bo26uMhleMXsDmnZ12eJLdrAZa9MANg==","shasum":"6ad4ca610f696098e92954ab431ff83bea0ce13f"}},"2.1.1":{"repository":{"url":"git+https://github.com/sindresorhus/is.git","type":"git"},"license":"MIT","dist":{"integrity":"sha512-/aPsuoj/1Dw/kzhkgz+ES6TxG0zfTMGLwuK2ZG00k/iJzYHTLCE8mVU8EPqEOp/lmxPoq1C1C9RYToRKb2KEfg==","shasum":"ceff6a28a5b4867c2dd4a1ba513de278ccbe8bb1"}},"3.0.0":{"repository":{"url":"git+https://github.com/sindresorhus/is.git","type":"git"},"license":"MIT","dist":{"integrity":"sha512-kqA5I6Yun7PBHk8WN9BBP1c7FfN2SrD05GuVSEYPqDb4nerv7HqYfgBfMIKmT/EuejURkJKLZuLyGKGs6WEG9w==","shasum":"78fabc5e295adb6e1ef57eaafe4cc5d7aa35b183"}},"3.1.0":{"repository":{"url":"git+https://github.com/sindresorhus/is.git","type":"git"},"license":"MIT","dist":{"integrity":"sha512-n4J+zu52VdY43kdi/XdI9DzuMr1Mur8zFL5ZRG2opCans9aiFwkPxHYFEb5Xgy7n1Z4K6WfI4FpqUqsh3E8BPQ==","shasum":"d8735532635bea69ad39119df5f0f10099bd09dc"}},"3.1.1":{"repository":{"url":"git+https://github.com/sindresorhus/is.git","type":"git"},"license":"MIT","dist":{"integrity":"sha512-tLnujxFtfH7F+i5ghUfgGlJsvyCKvUnSMFMlWybFdX9/DdX8svb4Zwx1gV0gkkVCHXtmPSetoAR3QlKfOld6Tw==","shasum":"6e39e4222add8b362da35720c9dd5d53345d5851"}},"3.1.2":{"repository":{"url":"git+https://github.com/sindresorhus/is.git","type":"git"},"license":"MIT","dist":{"integrity":"sha512-JiX9vxoKMmu8Y3Zr2RVathBL1Cdu4Nt4MuNWemt1Nc06A0RAin9c5FArkhGsyMBWfCu4zj+9b+GxtjAnE4qqLQ==","shasum":"548650de521b344e3781fbdb0ece4aa6f729afb8"}},"4.0.0":{"repository":{"url":"git+https://github.com/sindresorhus/is.git","type":"git"},"license":"MIT","dist":{"integrity":"sha512-FyD2meJpDPjyNQejSjvnhpgI/azsQkA4lGbuu5BQZfjvJ9cbRZXzeWL2HceCekW4lixO9JPesIIQkSoLjeJHNQ==","shasum":"2ff674e9611b45b528896d820d3d7a812de2f0e4"}},"4.0.1":{"repository":{"url":"git+https://github.com/sindresorhus/is.git","type":"git"},"license":"MIT","dist":{"integrity":"sha512-Qm9hBEBu18wt1PO2flE7LPb30BHMQt1eQgbV76YntdNk73XZGpn3izvGTYxbGgzXKgbCjiia0uxTd3aTNQrY/g==","shasum":"d26729db850fa327b7cacc5522252194404226f5"}},"4.1.0":{"repository":{"url":"git+https://github.com/sindresorhus/is.git","type":"git"},"license":"MIT","dist":{"integrity":"sha512-Cgva8HxclecUCmAImsWsbZGUh6p5DSzQ8l2Uzxuj9ANiD7LVhLM1UJ2hX/R2Y+ILpvqgW9QjmTCaBkXtj8+UOg==","shasum":"3853c0c48b47f0ebcdd3cd9a66fdd0d277173e78"}},"4.2.0":{"repository":{"url":"git+https://github.com/sindresorhus/is.git","type":"git"},"license":"MIT","dist":{"integrity":"sha512-VkE3KLBmJwcCaVARtQpfuKcKv8gcBmUubrfHGF84dXuuW6jgsRYxPtzcIhPyK9WAPpRt2/xY6zkD9MnRaJzSyw==","shasum":"667bfc6186ae7c9e0b45a08960c551437176e1ca"}},"4.2.1":{"repository":{"url":"git+https://github.com/sindresorhus/is.git","type":"git"},"license":"MIT","dist":{"integrity":"sha512-BrzrgtaqEre0qfvI8sMTaEvx+bayuhPmfe2rfeUGPPHYr/PLxCOqkOe4TQTDPb+qcqgNcsAtXV/Ew74mcDIE8w==","shasum":"b88b5724283db80b507cd612caee9a1947412a20"}},"4.3.0":{"repository":{"url":"git+https://github.com/sindresorhus/is.git","type":"git"},"license":"MIT","dist":{"integrity":"sha512-wwOvh0eO3PiTEivGJWiZ+b946SlMSb4pe+y+Ur/4S87cwo09pYi+FWHHnbrM3W9W7cBYKDqQXcrFYjYUCOJUEQ==","shasum":"344fd9bf808a84567ba563d00cc54b2f428dbab1"}},"4.4.0":{"repository":{"url":"git+https://github.com/sindresorhus/is.git","type":"git"},"license":"MIT","dist":{"integrity":"sha512-QppPM/8l3Mawvh4rn9CNEYIU9bxpXUCRMaX9yUpvBk1nMKusLKpfXGDEKExKaPhLzcn3lzil7pR6rnJ11HgeRQ==","shasum":"e277e5bdbdf7cb1e20d320f02f5e2ed113cd3185"}},"4.5.0":{"repository":{"url":"git+https://github.com/sindresorhus/is.git","type":"git"},"license":"MIT","dist":{"integrity":"sha512-ZzlL5VTnHZJl8wMWEaYk/13hwMNKLylTSPZRz8+0HIwfRTQMnFgUahDNRRV+rTmPADxQZYxna/nQcStNSCccKg==","shasum":"7c8293e2268de42d7037249a9e4f905dc890539b"}},"4.6.0":{"repository":{"url":"git+https://github.com/sindresorhus/is.git","type":"git"},"license":"MIT","dist":{"integrity":"sha512-t09vSN3MdfsyCHoFcTRCH/iUtG7OJ0CsjzB8cjAmKc/va/kIgeDI/TxsigdncE/4be734m0cvIYwNaV4i2XqAw==","shasum":"3c7c9c46e678feefe7a2e5bb609d3dbd665ffb3f"}},"5.0.0":{"repository":{"url":"git+https://github.com/sindresorhus/is.git","type":"git"},"license":"MIT","dist":{"integrity":"sha512-AFY4d1/eSXxTBtWg0CFzuV5ekeaeN1QZ7AmwttlulptP2Xw1pVcSxMt/F2HWWhg7TfjE0XhtXFm3Z2j61DbeXA==","shasum":"bbcc0973de6aef308dc2d4898bf28b03f38dbc7f"}},"5.0.1":{"repository":{"url":"git+https://github.com/sindresorhus/is.git","type":"git"},"license":"MIT","dist":{"integrity":"sha512-Jk18MsUvuX+PUw3/ia0vA3ZJeHa1h5nsHSHPztLNA/RN9LkwfPhXe3wa9/aFJg6MvrPADqetXyQVE5BPkQx7Xw==","shasum":"0e54d0a471a675453f7ac3f618acb81622155c21"}},"5.1.0":{"repository":{"url":"git+https://github.com/sindresorhus/is.git","type":"git"},"license":"MIT","dist":{"integrity":"sha512-TsEUyp3jzFpAMVO/+iFt+8nRoGJcU9ZE4mfyi3SpFry8j6CaxzLDuC7HefHCQ9/+IykpypZanfPPfeHpUAziyg==","shasum":"d2b56c5eb1619fca9be94ced04ffafde8107a9e1"}},"5.2.0":{"repository":{"url":"git+https://github.com/sindresorhus/is.git","type":"git"},"license":"MIT","dist":{"integrity":"sha512-tDrSvtear91yf6HFlHHwpV5x4ZyzFj3xkZxsfmsuLlQwR4e0+n8Da1Dr+TIY6nla0ATGxqLK9MWz7Dx/jlu9RQ==","shasum":"2d1acdf153e59bc6e865adf5c893dbf388a1789b"}},"5.3.0":{"repository":{"url":"git+https://github.com/sindresorhus/is.git","type":"git"},"license":"MIT","dist":{"integrity":"sha512-CX6t4SYQ37lzxicAqsBtxA3OseeoVrh9cSJ5PFYam0GksYlupRfy1A+Q4aYD3zvcfECLc0zO2u+ZnR2UYKvCrw==","shasum":"0ec9264cf54a527671d990eb874e030b55b70dcc"}},"5.4.0":{"repository":{"url":"git+https://github.com/sindresorhus/is.git","type":"git"},"license":"MIT","dist":{"integrity":"sha512-Ggh6E9AnMpiNXlbXfFUcWE9qm408rL8jDi7+PMBBx7TMbwEmiqAiSmZ+zydYwxcJLqPGNDoLc9mXDuMDBZg0sA==","shasum":"b1bfbd6024311ade045093b424536cefcc8e3a42"}},"5.4.1":{"repository":{"url":"git+https://github.com/sindresorhus/is.git","type":"git"},"license":"MIT","dist":{"integrity":"sha512-axlrvsHlHlFmKKMEg4VyvMzFr93JWJj4eIfXY1STVuO2fsImCa7ncaiG5gC8HKOX590AW5RtRsC41/B+OfrSqw==","shasum":"c4383ce702fb90531c3d310506bab89e70427c53"}},"5.5.0":{"repository":{"url":"git+https://github.com/sindresorhus/is.git","type":"git"},"license":"MIT","dist":{"integrity":"sha512-3rO1QIz6mL0MvFVTOxqhDJRVsLfG/vK2VSlKKPghALA6FhJqU7L+RUHnFvH5BP5HhkWiMQqq514i9ZFTcqoGCQ==","shasum":"70af51f38ef3b624eb08eb02a2ed70f117fa19d7"}},"5.5.1":{"repository":{"url":"git+https://github.com/sindresorhus/is.git","type":"git"},"license":"MIT","dist":{"integrity":"sha512-wTsEUhqTXg1NDW+o9aWANj4LxELwWjqN0F3ltsWwpYoh0NSlMWo+u7FluRrSF2E2uaPYx7dJ3FnTf69git/0ug==","shasum":"a18b694ca8e9f45d64f578a4779568dd74d232b8"}},"5.5.2":{"repository":{"url":"git+https://github.com/sindresorhus/is.git","type":"git"},"license":"MIT","dist":{"integrity":"sha512-8ZMK+V6YpeZFfW6hU9uAeWVuq8v3t7BaG276gIO+kVqnAcLrHCXdFUOf7kgouyfAarkZtuavIqY3RsXTsTWviw==","shasum":"cbfd816d556b941f65d32cfc6d708359b826e7ea"}},"5.6.0":{"repository":{"url":"git+https://github.com/sindresorhus/is.git","type":"git"},"license":"MIT","dist":{"integrity":"sha512-TV7t8GKYaJWsn00tFDqBw8+Uqmr8A0fRU1tvTQhyZzGv0sJCGRQL3JGMI3ucuKo3XIZdUP+Lx7/gh2t3lewy7g==","shasum":"41dd6093d34652cddb5d5bdeee04eafc33826668"}},"6.0.0":{"repository":{"url":"git+https://github.com/sindresorhus/is.git","type":"git"},"license":"MIT","dist":{"integrity":"sha512-iVkg+3V+GJfof7yAHOxHyoiEfgpRJhnddOY3EsTM/uqwcm6M/jDQwK1n1nnraMpTRT36CxS0RCtJohggaQ0jgQ==","shasum":"06fa296f23affba79fc6a4b6e67c7742e85acd71"}},"6.0.1":{"repository":{"url":"git+https://github.com/sindresorhus/is.git","type":"git"},"license":"MIT","dist":{"integrity":"sha512-yLtFOyhTzjtHXgccpHlfz/HKtfXb43HQLTUfAZjSq9OZJZmbAVVLbYwG7dRSMw4C38249lkiZZ0flkdBRZl+lg==","shasum":"1abd5a02e962ed67057e1fd946f6c3e59b872ba1"}},"6.1.0":{"repository":{"url":"git+https://github.com/sindresorhus/is.git","type":"git"},"license":"MIT","dist":{"integrity":"sha512-BuvU07zq3tQ/2SIgBsEuxKYDyDjC0n7Zir52bpHy2xnBbW81+po43aLFPLbeV3HRAheFbGud1qgcqSYfhtHMAg==","shasum":"71a4ca5171888fb7fc36c6d1ff3604b0a5e43555"}},"6.2.0":{"repository":{"url":"git+https://github.com/sindresorhus/is.git","type":"git"},"license":"MIT","dist":{"integrity":"sha512-yM/IGPkVnYGblhDosFBwq0ZGdnVSBkNV4onUtipGMOjZd4kB6GAu3ys91aftSbyMHh6A2GPdt+KDI5NoWP63MQ==","shasum":"979e220a34e7403790f65cc7e381f6d50aeb8eea"}},"6.3.0":{"repository":{"url":"git+https://github.com/sindresorhus/is.git","type":"git"},"license":"MIT","dist":{"integrity":"sha512-bOSPck7aIJjASXIg1qvXSIjXhVBpIEKdl2Wxg4pVqoTRPL8wWExKBrnGIh6CEnhkFQHfc36k7APhO3uXV4g5xg==","shasum":"c67768a6d85668afef39af6425950a495f29a8ba"}},"6.3.1":{"repository":{"url":"git+https://github.com/sindresorhus/is.git","type":"git"},"license":"MIT","dist":{"integrity":"sha512-FX4MfcifwJyFOI2lPoX7PQxCqx8BG1HCho7WdiXwpEQx1Ycij0JxkfYtGK7yqNScrZGSlt6RE6sw8QYoH7eKnQ==","shasum":"43bbe2a94de0d7a11b95b7fc8100fa0e4694bbe0"}},"7.0.0":{"repository":{"url":"git+https://github.com/sindresorhus/is.git","type":"git"},"license":"MIT","dist":{"integrity":"sha512-WDTlVTyvFivSOuyvMeedzg2hdoBLZ3f1uNVuEida2Rl9BrfjrIRjWA/VZIrMRLvSwJYCAlCRA3usDt1THytxWQ==","shasum":"af4d8061cd325782355e7716633e03f7758d4f17"}},"7.0.1":{"repository":{"url":"git+https://github.com/sindresorhus/is.git","type":"git"},"license":"MIT","dist":{"integrity":"sha512-QWLl2P+rsCJeofkDNIT3WFmb6NrRud1SUYW8dIhXK/46XFV8Q/g7Bsvib0Askb0reRLe+WYPeeE+l5cH7SlkuQ==","shasum":"693cd0bfa7fdc71a3386b72088b660fb70851927"}},"7.0.2":{"repository":{"url":"git+https://github.com/sindresorhus/is.git","type":"git"},"license":"MIT","dist":{"integrity":"sha512-d9xRovfKNz1SKieM0qJdO+PQonjnnIfSNWfHYnBSJ9hkjm0ZPw6HlxscDXYstp3z+7V2GOFHc+J0CYrYTjqCJw==","shasum":"a0df078a8d29f9741503c5a9c302de474ec8564a"}},"7.1.0":{"repository":{"url":"git+https://github.com/sindresorhus/is.git","type":"git"},"license":"MIT","dist":{"integrity":"sha512-7F/yz2IphV39hiS2zB4QYVkivrptHHh0K8qJJd9HhuWSdvf8AN7NpebW3CcDZDBQsUPMoDKWsY2WWgW7bqOcfA==","shasum":"ae17a8f9188644a9be064e0e67932351f82fe967"}},"7.1.1":{"repository":{"url":"git+https://github.com/sindresorhus/is.git","type":"git"},"license":"MIT","dist":{"integrity":"sha512-rO92VvpgMc3kfiTjGT52LEtJ8Yc5kCWhZjLQ3LwlA4pSgPpQO7bVpYXParOD8Jwf+cVQECJo3yP/4I8aZtUQTQ==","shasum":"e32f9b1e0d7e14ee9504cdc7aae4a18dea8c3ef7"}},"7.2.0":{"repository":{"url":"git+https://github.com/sindresorhus/is.git","type":"git"},"license":"MIT","dist":{"integrity":"sha512-P1Cz1dWaFfR4IR+U13mqqiGsLFf1KbayybWwdd2vfctdV6hDpUkgCY0nKOLLTMSoRd/jJNjtbqzf13K8DCCXQw==","shasum":"7c594e1a64336d2008d99d814056d459421504d4"}},"8.0.0":{"repository":{"url":"git+https://github.com/sindresorhus/is.git","type":"git"},"license":"MIT","dist":{"integrity":"sha512-YvOsokBE5NsyHuXMnwEVB7lgFk6lX8F4OXCruYVgFII0hUHof0RGUvhMoabVt9hRqbg+qVzayzEG24RCcxcYeA==","shasum":"de0db6b7eb0dc97de15231ff4366fb509c2f4287"}},"8.1.0":{"repository":{"type":"git","url":"git+https://github.com/sindresorhus/is.git"},"license":"MIT","dist":{"integrity":"sha512-2SX/1jW6CIMAiebvVv5ZInoCEuWQmMyBoJXXGC6Vjakjp/fpxP5eHs7/V6WKuPEIbuK06+VpjH+vjLQhr98rDQ==","shasum":"00d7b9dc92664550fe933cdcfaa8665bc4111202"}}}}}