{"_cached_at":1778519098917,"v":{"_schema":2,"name":"dasherize","maintainer_names":["shahata"],"repository_url":"git://github.com/shahata/dasherize.git","license":"MIT","deprecated":null,"time":{"modified":"2022-06-14T18:40:03.260Z","created":"2014-07-18T20:05:34.547Z","1.0.0":"2014-07-18T20:05:34.547Z","2.0.0":"2015-08-21T00:26:34.450Z"},"versions_meta":{"1.0.0":{"repository":{"type":"git","url":"git://github.com/shahata/dasherize.git"},"license":"MIT","dist":{"integrity":"sha512-nUYAHZ2EspK2bwNvajnakobJ2DhyiPc3hlloKMoexiDycsG2q05+v3fSMnr3igy8pbBNUsUClQ4sGGDO0w894g==","shasum":"1310eaa8db3025f2fa53387f1021e5fda5423579"}},"2.0.0":{"repository":{"type":"git","url":"git://github.com/shahata/dasherize.git"},"license":"MIT","dist":{"integrity":"sha512-APql/TZ6FdLEpf2z7/X2a2zyqK8juYtqaSVqxw9mYoQ64CXkfU15AeLh8pUszT8+fnYjgm6t0aIYpWKJbnLkuA==","shasum":"6d809c9cd0cf7bb8952d80fc84fa13d47ddb1308"}}}}}